date_spacy/__init__.py
date_spacy/components.py
date_spacy-0.0.1.dist-info/METADATA
date_spacy-0.0.1.dist-info/WHEEL
date_spacy-0.0.1.dist-info/top_level.txt
date_spacy-0.0.1.dist-info/RECORD
