Metadata-Version: 2.1
Name: date-spacy
Version: 0.0.1
Summary: A spaCy extension for enhanced date and number entity recognition and extraction as structured data.
Home-page: https://github.com/wjbmattingly/date-spacy
Author: WJB Mattingly
Classifier: Programming Language :: Python
Classifier: Programming Language :: Python :: 3
Classifier: License :: OSI Approved :: MIT License
Classifier: Operating System :: OS Independent
Requires-Dist: spacy (>=3.0)
Requires-Dist: dateparser
